__init__.py
convergence_entropy/__init__.py
convergence_entropy/CEDA/__init__.py
convergence_entropy/CEDA/EDA/EDA.py
convergence_entropy/CEDA/EDA/TFIDF-v1.py
convergence_entropy/CEDA/EDA/TFIDF.py
convergence_entropy/CEDA/EDA/__init__.py
convergence_entropy/CEDA/EDA/recurrence_plot.py
convergence_entropy/CEDA/calc/__init__.py
convergence_entropy/CEDA/calc/end_to_end_analysis.py
convergence_entropy/CEDA/calc/entropy.py
convergence_entropy/CEDA/calc/fastGraph.py
convergence_entropy/CEDA/calc/model.py
convergence_entropy/CEDA/calc/wv_model.py
convergence_entropy/CEDA/calc/_bypass/__init__.py
convergence_entropy/CEDA/calc/_bypass/_experimental/__init__.py
convergence_entropy/CEDA/calc/_bypass/_experimental/deconstructed_cos/__init__.py
convergence_entropy/CEDA/calc/_bypass/_experimental/deconstructed_cos/end_to_end_analysis.py
convergence_entropy/CEDA/calc/_bypass/_experimental/deconstructed_cos/entropy.py
convergence_entropy/CEDA/calc/_bypass/_experimental/deconstructed_cos/fastGraph.py
convergence_entropy/CEDA/calc/_bypass/_experimental/deconstructed_cos/wv_model.py
convergence_entropy/CEDA/calc/_bypass/_old/__init__.py
convergence_entropy/CEDA/calc/_bypass/_old/entropy_deprecated.py
convergence_entropy/CEM/__init__.py
convergence_entropy/CEM/entropy.py
convergence_entropy/CEM/fastGraph.py
convergence_entropy/CEM/language_model.py
convergence_entropy/CEM/language_model_with_classifier.py
convergence_entropy/CEM/minimum_sequence_entropy.py
convergence_entropy/CEM/multi_level_language_model.py
convergence_entropy/CEM/_bypass/__init__.py
convergence_entropy/CEM/_bypass/entropy_deprecated.py
convergence_entropy_metric-1.3.dist-info/licenses/LICENSE
convergence_entropy_metric-1.3.dist-info/METADATA
convergence_entropy_metric-1.3.dist-info/WHEEL
convergence_entropy_metric-1.3.dist-info/top_level.txt
convergence_entropy_metric-1.3.dist-info/RECORD
