Metadata-Version: 2.4
Name: convergence_entropy_metric
Version: 1.3
Author: ZP Rosen
License-File: LICENSE
Dynamic: author
Dynamic: description
Dynamic: description-content-type
Dynamic: license-file
